{
    "cities": [
        {
            "cityId": "25-TR",
            "cityName": "Erzurum",
            "stations": [
                {
                    "stationId": "stop-541",
                    "stationsName": "Kyk Durağı",
                    "stationsLocation": "x1,y1"
                },
                {
                    "stationsId": "stop-542",
                    "stationsName": "Yurtlar Bölgesi Durağı",
                    "stationsLocation": "x2,y2"
                }
            ],
            "routes":[
                {
                    "routeId":"route-B3",
                    "routeName": "B3",
                    "routeLine": "Havuzbaşı - Dadaşkent",
                    "routeStations": ["KENT MEYDANI" , "KUDÜS CAD." , "ÇARK CAD." , "SANAYİ CAD." , "M.YAZICIOĞLU CAD." , "KENAN SOFUOĞLU CAD." , "N.FAZIL CAD." , "ÜNİVERSİTE CAD." , "KAMPÜS"],
                    "routeStart": ["x2,y2"],
                    "routeStop": ["x1,y1"]    
                }
            ],
            "populerPlaces": [
                {
                    "populerName": "Yakutiye Medresesi",
                    "description": "Erzurum'un tarihi medreselerinden biri olup Selçuklu dönemine aittir.",
                    "image": "https://i.imgur.com/UFEk5Hf.jpg"
                },
                {
                    "populerName": "Çifte Minareli Medrese",
                    "description": "Erzurum'un simgelerinden biri olan Selçuklu dönemi medresesi.",
                    "image": "https://i.imgur.com/MWQM74l.jpg"
                },
                {
                    "populerName": "Palandöken Kayak Merkezi",
                    "description": "Türkiye'nin en popüler kayak merkezlerinden biri.",
                    "image": "https://i.imgur.com/n1oBatv.jpg"
                },
                {
                    "populerName": "Tortum Şelalesi",
                    "description": "Türkiye'nin en büyük şelalelerinden biri olan doğal güzellik.",
                    "image": "https://i.imgur.com/U6qvHOO.jpg"
                },
                {
                    "populerName": "Tarihi Erzurum Evleri",
                    "description": "Osmanlı mimarisinin izlerini taşıyan tarihi Erzurum evleri.",
                    "image": "https://i.imgur.com/xjM1tOA.jpg"
                }
            ],
            "cardReloadPoints": [
                {
                    "pointName": "point1",
                    "location": "x1,y1"
                },
                {
                    "pointName": "point2",
                    "location": "x2,y2"
                }
            ]
        },
        {
            "cityId": "54-TR",
            "cityName": "Sakarya",
            "stations": [
                {
                    "stationId": "stop54-1",
                    "stationsName": "Demokrasi Meydanı",
                    "stationsLocation": "40.775660, 30.401123"
                },
                {
                    "stationsId": "stop54-2",
                    "stationsName": "Kudüs Caddesi",
                    "stationsLocation": "40.774400, 30.397276"
                },
                {
                    "stationId": "stop54-3",
                    "stationsName": "Kudüs Caddesi-1",
                    "stationsLocation": "40.773275, 30.393149"
                },
                {
                    "stationId": "stop54-4",
                    "stationsName": "Kudüs Caddesi-2",
                    "stationsLocation": "40.774024, 30.389604"
                },
                {
                    "stationId": "stop54-5",
                    "stationsName": "Millet Bahçesi",
                    "stationsLocation": "40.775398, 30.385649"
                },
                {
                    "stationId": "stop54-6",
                    "stationsName": "Çark Köprü-1",
                    "stationsLocation": "40.775006, 30.383662"
                },
                {
                    "stationId": "stop54-7",
                    "stationsName": "Çark Caddesi-2",
                    "stationsLocation": "40.774098, 30.380993"
                },
                {
                    "stationId": "stop54-8",
                    "stationsName": "Hakkı Demir Ortaokulu-1",
                    "stationsLocation": "40.772016, 30.379829"
                },
                {
                    "stationId": "stop54-9",
                    "stationsName": "Çark Sanayi-1",
                    "stationsLocation": "40.769798, 30.378093"
                },
                {
                    "stationId": "stop54-10",
                    "stationsName": "Altınova Durağı",
                    "stationsLocation": "40.768356, 30.376125"
                },
                {
                    "stationId": "stop54-11",
                    "stationsName": "Serdivan Devlet Hastanesi",
                    "stationsLocation": "40.765937, 30.372840"
                },
                {
                    "stationId": "stop54-12",
                    "stationsName": "Muhsin Yazıcıoğlu Bulvarı-2",
                    "stationsLocation": "40.764236, 30.370512"
                },
                {
                    "stationId": "stop54-13",
                    "stationsName": "Muhsin Yazıcıoğlu Bulvarı-4",
                    "stationsLocation": "40.762567, 30.368241"
                },
                {
                    "stationId": "stop54-14",
                    "stationsName": "Muhsin Yazıcıoğlu Bulvarı-6",
                    "stationsLocation": "40.760690, 30.365680"
                },
                {
                    "stationId": "stop54-15",
                    "stationsName": "Darboğaz Durağı",
                    "stationsLocation": "40.757568, 30.364023"
                },
                {
                    "stationId": "stop54-16",
                    "stationsName": "165. Sokak Durağı-1",
                    "stationsLocation": "40.755399, 30.363648"
                },
                {
                    "stationId": "stop54-17",
                    "stationsName": "Su Durağı-2",
                    "stationsLocation": "40.748975, 30.363209"
                },
                {
                    "stationId": "stop54-18",
                    "stationsName": "Su Yönetim Merkezi",
                    "stationsLocation": "40.747208, 30.362395"
                },
                {
                    "stationId": "stop54-19",
                    "stationsName": "Necip Fazıl Kısakürek Caddesi-6",
                    "stationsLocation": "40.747679, 30.359523"
                },
                {
                    "stationId": "stop54-20",
                    "stationsName": "Necip Fazıl Kısakürek Caddesi-4",
                    "stationsLocation": "40.747318, 30.357255"
                },
                {
                    "stationId": "stop54-21",
                    "stationsName": "Necip Fazıl Kısakürek Caddesi-2",
                    "stationsLocation": "40.747723, 30.353748"
                },
                {
                    "stationId": "stop54-22",
                    "stationsName": "KYK-1",
                    "stationsLocation": "40.747356, 30.351222"
                },
                {
                    "stationId": "stop54-23",
                    "stationsName": "15 Temmuz Şehitler Lisesi",
                    "stationsLocation": "40.746025, 30.346918"
                },
                {
                    "stationId": "stop54-24",
                    "stationsName": "Yurtlar Durağı-1",
                    "stationsLocation": "40.745279, 30.343271"
                },
                {
                    "stationId": "stop54-25",
                    "stationsName": "Kampüs-1",
                    "stationsLocation": "40.744507, 30.341158"
                },
                {
                    "stationId": "stop54-26",
                    "stationsName": "Besyo",
                    "stationsLocation": "40.743017, 30.337914"
                },
                {
                    "stationId": "stop54-27",
                    "stationsName": "Enstitü",
                    "stationsLocation": "40.742926, 30.333966"
                },
                {
                    "stationId": "stop54-28",
                    "stationsName": "Kampüs Kafeterya-1",
                    "stationsLocation": "40.744188, 30.331650"
                },
                {
                    "stationId": "stop54-29",
                    "stationsName": "Fen Bilimleri",
                    "stationsLocation": "40.745281, 30.328776"
                },
                {
                    "stationId": "stop54-30",
                    "stationsName": "Esentepe Giriş Kapısı",
                    "stationsLocation": "40.745050, 30.323810"
                },
                {
                    "stationId": "stop54-31",
                    "stationsName": "İlahiyat Fakültesi",
                    "stationsLocation": "40.743263, 30.323896"
                },
                {
                    "stationId": "stop54-32",
                    "stationsName": "Mühendislik Fakültesi-1",
                    "stationsLocation": "40.741753, 30.325701"
                },
                {
                    "stationId": "stop54-33",
                    "stationsName": "Kampüs",
                    "stationsLocation": "40.74041705549361, 30.328951696442072"
                }
            ],
            "routes":[
                {
                    "routeId":"route-26",
                    "routeName": "26",
                    "routeLine": "Kent Meydanı - Kampüs",
                    "routeStations": ["stop54-1", "stop54-2", "stop54-3", "stop54-4", "stop54-5", "stop54-6", "stop54-7", "stop54-8", "stop54-9", "stop54-10", "stop54-11", "stop54-12", "stop54-13", "stop54-14", "stop54-15", "stop54-16", "stop54-17", "stop54-18", "stop54-19", "stop54-20", "stop54-21", "stop54-22", "stop54-23", "stop54-24", "stop54-25", "stop54-26", "stop54-27", "stop54-28", "stop54-29", "stop54-30", "stop54-31", "stop54-32", "stop54-33"]
                },
                {
                    "routeId":"route-4",
                    "routeName": "4",
                    "routeLine": "Kent Meydanı - Kampüs",
                    "routeStations": ["stop54-1", "stop54-2", "stop54-3", "stop54-4", "stop54-5", "stop54-6", "stop54-7", "stop54-8", "stop54-9", "stop54-10", "stop54-11", "stop54-12", "stop54-13", "stop54-14", "stop54-15", "stop54-16", "stop54-17", "stop54-18", "stop54-19", "stop54-20", "stop54-21", "stop54-22", "stop54-23", "stop54-24", "stop54-25", "stop54-26", "stop54-27", "stop54-28", "stop54-29", "stop54-30", "stop54-31", "stop54-32", "stop54-33"]
                },
                {
                    "routeId":"route-15",
                    "routeName": "15",
                    "routeLine": "Kent Meydanı - Kampüs",
                    "routeStations": ["stop54-1", "stop54-2", "stop54-3", "stop54-4", "stop54-5", "stop54-6", "stop54-7", "stop54-8", "stop54-9", "stop54-10", "stop54-11", "stop54-12", "stop54-13", "stop54-14", "stop54-15", "stop54-16", "stop54-17", "stop54-18", "stop54-19", "stop54-20", "stop54-21", "stop54-22", "stop54-23", "stop54-24", "stop54-25", "stop54-26", "stop54-27", "stop54-28", "stop54-29", "stop54-30", "stop54-31", "stop54-32", "stop54-33"]
                },
                {
                    "routeId":"route-28",
                    "routeName": "28",
                    "routeLine": "Kent Meydanı - Kampüs",
                    "routeStations": ["stop54-1", "stop54-2", "stop54-3", "stop54-4", "stop54-5", "stop54-6", "stop54-7", "stop54-8", "stop54-9", "stop54-10", "stop54-11", "stop54-12", "stop54-13", "stop54-14", "stop54-15", "stop54-16", "stop54-17", "stop54-18", "stop54-19", "stop54-20", "stop54-21", "stop54-22", "stop54-23", "stop54-24", "stop54-25", "stop54-26", "stop54-27", "stop54-28", "stop54-29", "stop54-30", "stop54-31", "stop54-32", "stop54-33"]
                }
            ],
            "populerPlaces": [
                {
                    "populerName": "Poyrazlar Gölü",
                    "description": "Bozulmamış doğasıyla piknik, doğa yürüyüşü, yaban hayatı gözlemi ve spor aktiviteleri için ideal bir mekândır. 67 hektarlık alana ve 2.400 m sahil uzunluğuna sahiptir. Göl çevresi karaçam ve meşe ormanlarıyla kaplıdır. 154 kuş türüne ev sahipliği yapar, ayrıca çakal, tilki, sincaptan yeşil kertenkeleye kadar birçok hayvan türü barındırır. Bisiklet sürüşü, festivaller ve yeme-içme imkânları mevcuttur. Doğal Sit Alanı olarak koruma altındadır ve her mevsim ulaşılabilir.",
                    "image": "https://i.imgur.com/ivpmJpG.jpg"
                },
                {
                    "populerName": "Sakarya Müzesi",
                    "description": "Sakarya Müzesi, Atatürk Evi olarak da bilinen ve Mustafa Kemal Atatürk'ün Sakarya ziyareti sırasında konakladığı evin restore edilmesiyle ziyarete açılmış bir müzedir. Sakarya ve çevresinde gerçekleştirilen arkeolojik kazılarda elde edilen, Roma ve Osmanlı dönemine kadar uzanan birçok değerli eserin sergilendiği müze, şehrin kültürel mirasını ve yüzyıllar boyunca şekillenen yaşam tarzını yansıtan bir etnografya bölümüne de ev sahipliği yapmaktadır. Geniş bahçesi, özellikle Helenistik, Roma ve Bizans dönemlerine ait sağlam kalmış antik lahitler, büyük heykeller ve taş eserlerle zenginleştirilmiştir. Şehir merkezine yürüme mesafesinde yer alan Sakarya Müzesi, ziyaretçilere tarih ve kültürle iç içe bir deneyim sunmaktadır.",
                    "image": "https://i.imgur.com/pud0cL7.jpg"
                },
                {
                    "populerName": "Aziz Duran Parkı",
                    "description": "Aziz Duran Parkı, Çark Deresi kenarında kent park olarak da bilinen turistlerin ve yerli halkın en çok ziyaret ettiği yerlerden biridir. Park, yürüyüş parkurları, koşu yolları, çocuk oyun alanları, kır bahçeleri ve restoranlar gibi pek çok imkân sunmaktadır. Yaz aylarında deniz bisikleti ve kano gibi aktivitelerin yapılabildiği göleti, spor sahaları, tenis kortları ve kapalı yüzme havuzlarıyla spor tutkunları için ideal bir mekândır. Ayrıca parkın içerisinde bulunan, Tarihi Çark değiirmeni bulunmaktadır. 1581-1585 yılları arasında inşa edilen bu ahşap değirmen, 250 yıldan uzun süre şehre hizmet ettikten sonra 18. yüzyılda bir gezi alanına dönüştürülmüştür. Osmanlı döneminde camilere ve Adapazarı'na içme suyu taşımak amacıyla kullanılan çark, günümüzde hem tarihi değeri hem de estetik yapısıyla ziyaretçileri ağırlamaktadır.",
                    "image": "https://i.imgur.com/BGqI19C.jpg"
                },
                {
                    "populerName": "Arifiye Gölya Tabiat Parkı",
                    "description": "Sakarya şehir merkezine yalnızca 7 kilometre uzaklıkta, Sakarya Nehri kıyısında bulunan Arifiye Gölya Tabiat Parkı, büyüleyici nehir manzaraları, mesire alanları, 2 kilometreden uzun yürüyüş parkurları, bisiklet yolları ve çocuk oyun alanları ile ziyaretçilerin ilgisini çeken bir cazibe merkezidir. Özellikle hafta sonları, aileler tarafından sıklıkla tercih edilen bu doğal alan, bahar aylarında Sakarya Nehri'nin etkileyici manzaralarının fotoğraflarını çekmek veya yaz aylarında serin havasında piknik yaparak keyifli vakit geçirmek için ideal bir noktadır. Doğa ve huzur arayanlar için Arifiye Gölya Tabiat Parkı, Sakarya’da mutlaka ziyaret edilmesi gereken yerler arasında bulunmaktadır.",
                    "image": "https://i.imgur.com/axtAUMC.jpg"
                },
                {
                    "populerName": "Sakarya Park",
                    "description": "2014 yılında hizmete açılan Sakarya Park, ziyaretçilerine çeşitli olanaklar sunmaktadır. Park içerisinde çocuk oyun alanları, spor sahaları, yürüyüş ve koşu yolları, seyir terasları, kafeteryalar, restoranlar ve kır bahçeleri bulunmaktadır. Ayrıca park, Necip Fazıl Anıtı'na da ev sahipliği yapmaktadır. Özellikle hafta sonları spor yapmak veya çocuklarla keyifli vakit geçirmek isteyen aileler tarafından sıklıkla tercih edilen Sakarya Park, şehir yaşamından uzaklaşıp huzurlu bir ortamda vakit geçirmek isteyenler için ideal bir seçenektir.",
                    "image": "https://i.imgur.com/2DIFI8g.jpg"
                },
                {
                    "populerName": "Sakarya İl Ormanı Tabiat Parkı",
                    "description": "Doğal güzelliklerini korumak amacıyla 2011 yılında milli park ilan edilen Sakarya İl Ormanı Tabiat Parkı, şehir merkezine 12 kilometre uzaklıkta yer almaktadır. Endemik bitki türleri ve onlarca çeşit ağacıyla doğa severleri büyüleyen bu tabiat parkı, ziyaretçilerine kamp ve karavan alanları, yürüyüş parkurları, bisiklet yolları, mesire alanları, restoranlar ve marketler gibi pek çok olanak sunmaktadır. Park, tertemiz havasında organik ürünlerle hazırlanan köy kahvaltıları ile dikkat çekerken, ziyaretçiler ATV ve bisiklet turlarıyla bölgenin doğal güzelliklerini keşfedebilirler. Orman köşkleri ve bungalov evlerde konaklama imkanı sunan tabiat parkı, doğayla baş başa sakin ve dinlendirici bir tatil için ideal bir destinasyondur.",
                    "image": "https://i.imgur.com/hilZG0g.jpg"
                },
                {
                    "populerName": "Sapanca Gölü",
                    "description": "Sadece Sakarya’nın değil, Türkiye’nin de en önemli doğal güzelliklerinden biri olan Sapanca Gölü, 16 kilometre uzunluğuyla dikkat çekmektedir. İstanbul gibi büyük şehirlere yakın konumu sayesinde hafta sonu gezileri ve doğa tatilleri için sıkça tercih edilen bu tatlı su gölü, çevresini saran yürüyüş ve bisiklet yolları, kır bahçeleri, mesire alanları ve doğa otelleriyle gelişmiş turizm olanakları sunmaktadır. Tertemiz kar sularıyla zengin balık çeşitliliğine sahip olan Sapanca Gölü, her mevsim balık avlama turları, bahar ve yaz aylarında ise kano gezileri için idealdir. Gölde, onlarca su kuşu ve göçmen kuş türünü gözlemlemek ve fotoğraf safarilerine katılmak mümkündür. Dünya genelinden kampçıların her mevsim ziyaret ettiği bu büyüleyici göl, Sakarya’da mutlaka görülmesi gereken yerlerin başında gelmektedir.",
                    "image": "https://i.imgur.com/q0Hf6OT.jpg"
                },
                {
                    "populerName": "Taraklı",
                    "description": "Sakarya’nın tarihi ve doğal güzelliklerini korumayı başaran en özel ilçelerinden biri olan Taraklı, yüzlerce yıllık iki katlı klasik konaklarıyla ünlüdür. Arnavut kaldırımlı sokaklarını süsleyen taş ve ahşap mimarisiyle dikkat çeken evler, fotoğraf tutkunlarının vazgeçilmez adreslerinden biridir. İlçe, Yavuz Sultan Selim’in Mısır Seferi sırasında inşa ettirilen Yunus Paşa Camii gibi Osmanlı dönemi mimarisinin eşsiz örneklerini barındırır. Ayrıca, şifalı kaynak sularıyla günümüzde de hizmet vermeye devam eden Tarihi Hamam, mutlaka görülmesi gereken yerler arasındadır. M.Ö. 1000 ile M.Ö. 2000 yılları arasında yapıldığı düşünülen ve eşsiz panoramik manzaralarıyla bilinen Hisar Tepesi, Taraklı’da keyifle gezebileceğiniz bir diğer önemli noktadır. İlçe, tarihi dokusu ve doğal güzellikleriyle ziyaretçilerine benzersiz bir deneyim sunmaktadır.",
                    "image": "https://i.imgur.com/EdNQnsI.jpg"
                },
                {
                    "populerName": "Acarlar Longozu",
                    "description": "Türkiye’nin en büyük longoz ormanı olarak dikkat çekmektedir. Yaklaşık 1500 hektarlık bir alanı kaplayan ve 7,5 kilometre uzunluğa sahip bu eşsiz doğal alan, benzersiz manzaralarıyla ziyaretçilerini büyülemektedir. Doğa severler için vazgeçilmez bir durak olan Acarlar Longoz Ormanı, Okçu Deresi’nin huzur veren manzarası eşliğinde uzanan yürüyüş yolları, donanımlı kamp alanları ve seyir teraslarıyla her mevsim görülmeye değer bir güzellik sunar. Longoz, zengin aktiviteleriyle de öne çıkmaktadır. Doğa yürüyüşleri, rehberli turlar, kuş gözlemleri, fotoğraf safarileri, balık avlama turları, tekne gezileri ve bisiklet turları gibi etkinliklerle doğayla iç içe bir deneyim sunar. Özellikle göçmen kuşların üreme ve kışlama alanı olarak büyük öneme sahip olan Acarlar Longozu, aynı zamanda su menekşesi, su lalesi ve nilüferler gibi birçok endemik bitki türüyle büyüleyici manzaralar oluşturur. Doğal zenginlikleri ve sunduğu imkanlarıyla Acarlar Longozu, Sakarya’da mutlaka ziyaret edilmesi gereken yerler arasında yer almaktadır.",
                    "image": "https://i.imgur.com/CEYIqDx.jpg"
                },
                {
                    "populerName": "Justinianos Köprüsü",
                    "description": "Sakarya’nın Serdivan ilçesinde yer alan Beşköprü (Justinianos Köprüsü), Geç Roma Dönemi'ne ait önemli bir tarihi eserdir. Konstantinopolis ile Anadolu şehirleri arasında ulaşım sağlanması amacıyla inşa edilen köprü, Sakarya Nehri üzerinde kesme taşlarla yapılmış ve 12 kemeriyle dönemin mühendislik becerisini yansıtan etkileyici bir yapıdır. 365 metre uzunluğunda olan bu köprü, günümüze kadar sağlam kalmayı başararak tarihi bir simge haline gelmiştir. Gün batımında sunduğu eşsiz manzaralarla fotoğraf meraklıları tarafından sıkça ziyaret edilen Beşköprü, hem doğa hem de tarih gezilerinin uğrak noktalarından biri olmaktadır.",
                    "image": "https://i.imgur.com/lKsySzd.jpg"
                },
                {
                    "populerName": "Sakarya Nehri",
                    "description": "Sakarya Nehri, Kızılırmak ve Fırat nehirlerinden sonra Türkiye’nin üçüncü en uzun akarsuyu olup, Sakarya’nın en önemli doğal zenginliklerinden biridir. Etrafındaki yeşil alanlarla çevrili olan nehir, ziyaretçilerine huzur verici bir atmosfer sunmaktadır. Nehir kenarında yürüyüş yapabilir, balık tutabilir veya piknik yapabilirsiniz. Ayrıca, teknelerle yapılan turlara katılarak nehrin güzelliklerini farklı bir perspektiften keşfetme imkanı bulabilirsiniz. Sakarya Nehri üzerinde yer alan Justinianus Köprüsü (Beşköprü), şehrin tarihi miraslarından biri olarak mutlaka görülmesi gereken bir yapıdır. Bizans İmparatoru Justinianus tarafından MS 558-560 yıllarında inşa ettirilen bu taş köprü, 365 metre uzunluğunda ve 9,85 metre genişliğindedir. 12 kemerli yapısıyla erken Bizans Dönemi’nin Anadolu’daki en görkemli anıtsal yapılarından biri olan köprü, Sapanca Gölü’nün sularını Sakarya Nehri’ne boşaltan Çark Deresi üzerinde yer almaktadır. 2018 yılında UNESCO Dünya Miras Geçici Listesi’ne dahil edilen Justinianus Köprüsü, Sakarya şehir merkezine oldukça yakın olan Adapazarı ilçesinde ziyaretçilerini beklemektedir.",
                    "image": "https://i.imgur.com/xEzSZWB.jpg"
                },
                {
                    "populerName": "Karasu Sahil Parkı",
                    "description": "Sakarya'nın Karasu ilçesinde yer alan Karasu Sahil Parkı, 20 kilometre boyunca uzanan ince kumlu sahiliyle, Ege ve Akdeniz sahillerini aratmayan güzellikte bir tatil rotası sunmaktadır. Büyüleyici Karadeniz manzaraları eşliğinde ilerleyen yürüyüş parkurları, yol üzerindeki kafeler, restoranlar ve otelleriyle özellikle yaz aylarında oldukça canlı ve popüler bir destinasyondur. 300 metre uzunluğunda ve 100 metre genişliğindeki Karasu Sahil Parkı Plajı, ince kumlarıyla güneşlenmek veya tertemiz denizin keyfini çıkarmak için ideal bir yerdir. Akşamları yürüyüş yapmak ve spor yapmak için de tercih edilen Karasu Sahil Parkı, aynı zamanda kızıl gün batımı manzarası eşliğinde dinlendirici bir molanın verilebileceği mükemmel bir yerdir.",
                    "image": "https://i.imgur.com/zLrXRp2.jpg"
                },
                {
                    "populerName": "Serdivan Gölpark",
                    "description": "Sapanca Gölü’nün kenarında yer alan Serdivan Gölpark, eşsiz göl manzarası ve oksijen seviyesi yüksek havasıyla, Sakarya’da mutlaka ziyaret edilmesi gereken yerler arasında yer almaktadır. Şehir merkezine sadece 10 kilometre mesafede bulunan Gölpark, minibüslerle kolayca ulaşılabilen, doğayla iç içe bir mekan sunuyor. 8,5 kilometrelik kıyı şeridi, yürüyüş yapmak isteyenler için en çok tercih edilen alanlardan biridir. Gölün içine doğru uzanan ahşap iskeleler, seyir terasları, kır bahçeleri ve kilometrelerce uzanan yürüyüş yolları ile her mevsim popüler olan Serdivan Gölpark, yaz aylarında düzenlenen konserler ve tiyatro gösterileri ile de oldukça canlıdır. Geniş çocuk oyun alanları ve mesire yerleriyle, özellikle çocuklu aileler için ideal bir mekan olan Gölpark’a, Serdivan ilçesinden ücretsiz servisler ile de ulaşmak mümkündür.",
                    "image": "https://i.imgur.com/RtOLRwB.jpg"
                },
                {
                    "populerName": "Deprem ve Kültür Müzesi",
                    "description": "Sakarya’da mutlaka görmeni önerdiğimiz etkileyici müzelerden biri Deprem ve Kültür Müzesi’dir. 1967 ve 1999 yıllarında yaşanan yıkıcı büyük depremlerle acı bir geçmişe sahip olan Sakarya, bu depremlerin izlerini müzenin zengin koleksiyonlarında yakından gözler önüne seriyor. 1. derece deprem kuşağında yer alan Sakarya’da, geçmiş depremlerden ders çıkararak ve olası yeni depremler için hazırlıklı olmak amacıyla düzenlenen konferanslar, söyleşiler, atölyeler ve eğitimler de müzenin önemli etkinlikleri arasında yer alıyor. Depremle ilgili çarpıcı fotoğraf ve resim sergileri, ziyaretçilere derin bir farkındalık kazandırıyor.",
                    "image": "https://i.imgur.com/78yhjna.jpg"
                }

            ],
            "cardReloadPoints": [
                {
                    "pointName": "point1",
                    "location": "x1,y1"
                },
                {
                    "pointName": "point2",
                    "location": "x2,y2"
                }
            ]
        }
    ]
}
